gdcdictionary/__init__.py
gdcdictionary/examples/invalid/aliquot_invalid_1.json
gdcdictionary/examples/invalid/aliquot_invalid_2.json
gdcdictionary/examples/invalid/aliquot_invalid_3.json
gdcdictionary/examples/invalid/case_invalid_1.json
gdcdictionary/examples/invalid/case_invalid_2.json
gdcdictionary/examples/valid/acknowledgement.json
gdcdictionary/examples/valid/aligned_reads_index.json
gdcdictionary/examples/valid/aliquot.json
gdcdictionary/examples/valid/case.json
gdcdictionary/examples/valid/clinical_test.json
gdcdictionary/examples/valid/demographic.json
gdcdictionary/examples/valid/diagnosis.json
gdcdictionary/examples/valid/experiment.json
gdcdictionary/examples/valid/experimental_metadata.json
gdcdictionary/examples/valid/exposure.json
gdcdictionary/examples/valid/family_history.json
gdcdictionary/examples/valid/keyword.json
gdcdictionary/examples/valid/program.json
gdcdictionary/examples/valid/project.json
gdcdictionary/examples/valid/publication.json
gdcdictionary/examples/valid/read_group.json
gdcdictionary/examples/valid/read_group_qc.json
gdcdictionary/examples/valid/sample.json
gdcdictionary/examples/valid/slide.json
gdcdictionary/examples/valid/slide_count.json
gdcdictionary/examples/valid/slide_image.json
gdcdictionary/examples/valid/submitted_aligned_reads.json
gdcdictionary/examples/valid/submitted_copy_number.json
gdcdictionary/examples/valid/submitted_methylation.json
gdcdictionary/examples/valid/submitted_somatic_mutation.json
gdcdictionary/examples/valid/submitted_unaligned_reads.json
gdcdictionary/examples/valid/treatment.json
gdcdictionary/schema_test.py
gdcdictionary/schemas/README.md
gdcdictionary/schemas/_definitions.yaml
gdcdictionary/schemas/_settings.yaml
gdcdictionary/schemas/_terms.yaml
gdcdictionary/schemas/acknowledgement.yaml
gdcdictionary/schemas/aligned_reads_index.yaml
gdcdictionary/schemas/aliquot.yaml
gdcdictionary/schemas/case.yaml
gdcdictionary/schemas/clinical_test.yaml
gen3dictionary-3.0.0.dist-info/METADATA
gen3dictionary-3.0.0.dist-info/WHEEL
gen3dictionary-3.0.0.dist-info/licenses/LICENSE
gen3dictionary-3.0.0.dist-info/licenses/NOTICE
gen3dictionary-3.0.0.dist-info/RECORD
